dragonking/DK_test.py
dragonking/__init__.py
dragonking/moreDKtests.py
dragonking-0.1.0.dist-info/LICENSE
dragonking-0.1.0.dist-info/METADATA
dragonking-0.1.0.dist-info/WHEEL
dragonking-0.1.0.dist-info/top_level.txt
dragonking-0.1.0.dist-info/RECORD
