Metadata-Version: 2.1
Name: dragonking
Version: 0.1.0
Summary: Statistical tests for identification of dragon kings
Home-page: https://github.com/dcqin17/dragonking
Author: Daniel Qin, Raoul R. Wadhwa, Peter Erdi
Author-email: k17dq01@kzoo.edu
License: UNKNOWN
Platform: UNKNOWN
Classifier: Programming Language :: Python :: 2.7
Classifier: License :: OSI Approved :: MIT License
Classifier: Operating System :: OS Independent
